artile/__init__.py
artile/main.py
artile-0.1.0.dist-info/LICENSE
artile-0.1.0.dist-info/METADATA
artile-0.1.0.dist-info/WHEEL
artile-0.1.0.dist-info/RECORD
